rampwf/__init__.py
rampwf/_version.py
rampwf/cvs/__init__.py
rampwf/cvs/clustering.py
rampwf/cvs/time_series.py
rampwf/externals/__init__.py
rampwf/externals/tabulate.py
rampwf/externals/colored/__init__.py
rampwf/externals/colored/back.py
rampwf/externals/colored/colored.py
rampwf/externals/colored/colors.py
rampwf/externals/colored/fore.py
rampwf/externals/colored/hex.py
rampwf/externals/colored/style.py
rampwf/hyperopt/__init__.py
rampwf/hyperopt/hyperopt.py
rampwf/hyperopt/cli/__init__.py
rampwf/hyperopt/cli/hyperopt.py
rampwf/hyperopt/tests/__init__.py
rampwf/hyperopt/tests/test_hyperparameter.py
rampwf/prediction_types/__init__.py
rampwf/prediction_types/base.py
rampwf/prediction_types/clustering.py
rampwf/prediction_types/combined.py
rampwf/prediction_types/detection.py
rampwf/prediction_types/multiclass.py
rampwf/prediction_types/regression.py
rampwf/prediction_types/tests/__init__.py
rampwf/prediction_types/tests/test_detection_predictions.py
rampwf/prediction_types/tests/test_mixed_predictions.py
rampwf/prediction_types/tests/test_multiclass_predictions.py
rampwf/prediction_types/tests/test_regression_predictions.py
rampwf/score_types/__init__.py
rampwf/score_types/accuracy.py
rampwf/score_types/balanced_accuracy.py
rampwf/score_types/base.py
rampwf/score_types/brier_score.py
rampwf/score_types/classification_error.py
rampwf/score_types/classifier_base.py
rampwf/score_types/clustering_efficiency.py
rampwf/score_types/combined.py
rampwf/score_types/f1_above.py
rampwf/score_types/macro_averaged_recall.py
rampwf/score_types/make_combined.py
rampwf/score_types/mare.py
rampwf/score_types/negative_log_likelihood.py
rampwf/score_types/normalized_gini.py
rampwf/score_types/normalized_rmse.py
rampwf/score_types/relative_rmse.py
rampwf/score_types/rmse.py
rampwf/score_types/roc_auc.py
rampwf/score_types/soft_accuracy.py
rampwf/score_types/detection/__init__.py
rampwf/score_types/detection/average_precision.py
rampwf/score_types/detection/base.py
ramp_workflow-0.7.0.dist-info/LICENSE
ramp_workflow-0.7.0.dist-info/METADATA
ramp_workflow-0.7.0.dist-info/WHEEL
ramp_workflow-0.7.0.dist-info/entry_points.txt
ramp_workflow-0.7.0.dist-info/top_level.txt
ramp_workflow-0.7.0.dist-info/RECORD
